a_toad_emo/__init__.py
a_toad_emo/app_installer.py
a_toad_emo/app_runner.py
a_toad_emo/appium_runner.py
a_toad_emo/cli.py
a_toad_emo/config_loader.py
a_toad_emo/emulator_launcher.py
a_toad_emo-0.1.11.dist-info/LICENSE
a_toad_emo-0.1.11.dist-info/METADATA
a_toad_emo-0.1.11.dist-info/WHEEL
a_toad_emo-0.1.11.dist-info/entry_points.txt
a_toad_emo-0.1.11.dist-info/RECORD
