Metadata-Version: 2.3
Name: a-toad-emo
Version: 0.1.11
Summary: A CLI Tool to generate mobile applications demo video automatically.
License: MIT
Author: BlancJH
Requires-Python: >=3.11,<4.0
Classifier: License :: OSI Approved :: MIT License
Classifier: Programming Language :: Python :: 3
Classifier: Programming Language :: Python :: 3.11
Classifier: Programming Language :: Python :: 3.12
Classifier: Programming Language :: Python :: 3.13
Requires-Dist: appium-python-client (>=5.0.0,<6.0.0)
Requires-Dist: mypy (>=1.15.0,<2.0.0)
Requires-Dist: pytest (>=8.3.5,<9.0.0)
Requires-Dist: pyyaml (>=6.0.2,<7.0.0)
